AUTHORS.rst
CONTRIBUTING.rst
HISTORY.rst
LICENSE
MANIFEST.in
README.rst
setup.cfg
setup.py
docs/Makefile
docs/authors.rst
docs/conf.py
docs/contributing.rst
docs/history.rst
docs/index.rst
docs/installation.rst
docs/make.bat
docs/readme.rst
docs/usage.rst
microparcel_tools/__init__.py
microparcel_tools/__main__.py
microparcel_tools/cli.py
microparcel_tools/common.py
microparcel_tools/microparcel_tools.py
microparcel_tools/tools.py
microparcel_tools.egg-info/PKG-INFO
microparcel_tools.egg-info/SOURCES.txt
microparcel_tools.egg-info/dependency_links.txt
microparcel_tools.egg-info/entry_points.txt
microparcel_tools.egg-info/not-zip-safe
microparcel_tools.egg-info/requires.txt
microparcel_tools.egg-info/top_level.txt
tests/__init__.py
tests/test_microparcel_tools.py