Metadata-Version: 1.1
Name: microparcel-tools
Version: 0.0.1
Summary: Code generation tool for microparcel
Home-page: https://github.com/lukh/microparcel-tools
Author: Vivien Henry
Author-email: vivien.henry@outlook.fr
License: MIT license
Keywords: microparcel_tools
Platform: UNKNOWN
Classifier: Development Status :: 2 - Pre-Alpha
Classifier: Intended Audience :: Developers
Classifier: License :: OSI Approved :: MIT License
Classifier: Natural Language :: English
Classifier: Programming Language :: Python :: 3
Classifier: Programming Language :: Python :: 3.4
Classifier: Programming Language :: Python :: 3.5
Classifier: Programming Language :: Python :: 3.6
Classifier: Programming Language :: Python :: 3.7
